<annotation>
	<folder></folder>
	<filename>image_2147_jpg.rf.512ae670c675f8dff5d4e4d57e1ec83e.jpg</filename>
	<path>image_2147_jpg.rf.512ae670c675f8dff5d4e4d57e1ec83e.jpg</path>
	<source>
		<database>roboflow.ai</database>
	</source>
	<size>
		<width>1920</width>
		<height>1080</height>
		<depth>3</depth>
	</size>
	<segmented>0</segmented>
	<object>
		<name>Smoke</name>
		<pose>Unspecified</pose>
		<truncated>0</truncated>
		<difficult>0</difficult>
		<occluded>0</occluded>
		<bndbox>
			<xmin>631</xmin>
			<xmax>1028</xmax>
			<ymin>417</ymin>
			<ymax>620</ymax>
		</bndbox>
	</object>
</annotation>
