<annotation>
	<folder></folder>
	<filename>image_1189_jpg.rf.0e5a30b66237f5b67e61e93df5895316.jpg</filename>
	<path>image_1189_jpg.rf.0e5a30b66237f5b67e61e93df5895316.jpg</path>
	<source>
		<database>roboflow.ai</database>
	</source>
	<size>
		<width>1920</width>
		<height>1080</height>
		<depth>3</depth>
	</size>
	<segmented>0</segmented>
	<object>
		<name>Smoke</name>
		<pose>Unspecified</pose>
		<truncated>0</truncated>
		<difficult>0</difficult>
		<occluded>0</occluded>
		<bndbox>
			<xmin>1394</xmin>
			<xmax>1624</xmax>
			<ymin>443</ymin>
			<ymax>824</ymax>
		</bndbox>
	</object>
</annotation>
