<annotation>
	<folder></folder>
	<filename>image_587_jpg.rf.49ab51a5f0ee01750bd3e4a752e64cf9.jpg</filename>
	<path>image_587_jpg.rf.49ab51a5f0ee01750bd3e4a752e64cf9.jpg</path>
	<source>
		<database>roboflow.ai</database>
	</source>
	<size>
		<width>1920</width>
		<height>1080</height>
		<depth>3</depth>
	</size>
	<segmented>0</segmented>
	<object>
		<name>Smoke</name>
		<pose>Unspecified</pose>
		<truncated>0</truncated>
		<difficult>0</difficult>
		<occluded>0</occluded>
		<bndbox>
			<xmin>586</xmin>
			<xmax>686</xmax>
			<ymin>455</ymin>
			<ymax>545</ymax>
		</bndbox>
	</object>
</annotation>
