<annotation>
	<folder></folder>
	<filename>image_491_jpg.rf.fd9e1cb4830248f4e43e8f4427f85201.jpg</filename>
	<path>image_491_jpg.rf.fd9e1cb4830248f4e43e8f4427f85201.jpg</path>
	<source>
		<database>roboflow.ai</database>
	</source>
	<size>
		<width>1920</width>
		<height>1080</height>
		<depth>3</depth>
	</size>
	<segmented>0</segmented>
	<object>
		<name>instance_salient_object</name>
		<pose>Unspecified</pose>
		<truncated>0</truncated>
		<difficult>0</difficult>
		<occluded>0</occluded>
		<bndbox>
			<xmin>1052</xmin>
			<xmax>1110</xmax>
			<ymin>499</ymin>
			<ymax>546</ymax>
		</bndbox>
	</object>
	<object>
		<name>instance_salient_object</name>
		<pose>Unspecified</pose>
		<truncated>0</truncated>
		<difficult>0</difficult>
		<occluded>0</occluded>
		<bndbox>
			<xmin>626</xmin>
			<xmax>732</xmax>
			<ymin>430</ymin>
			<ymax>557</ymax>
		</bndbox>
	</object>
</annotation>
