<annotation>
	<folder></folder>
	<filename>image_578_jpg.rf.4ce6a2a0b8b7cfa3237c488c03f1d87f.jpg</filename>
	<path>image_578_jpg.rf.4ce6a2a0b8b7cfa3237c488c03f1d87f.jpg</path>
	<source>
		<database>roboflow.ai</database>
	</source>
	<size>
		<width>1920</width>
		<height>1080</height>
		<depth>3</depth>
	</size>
	<segmented>0</segmented>
	<object>
		<name>instance_salient_object</name>
		<pose>Unspecified</pose>
		<truncated>0</truncated>
		<difficult>0</difficult>
		<occluded>0</occluded>
		<bndbox>
			<xmin>618</xmin>
			<xmax>667</xmax>
			<ymin>462</ymin>
			<ymax>547</ymax>
		</bndbox>
	</object>
</annotation>
