<annotation>
	<folder></folder>
	<filename>image_1406_jpg.rf.f3963a2c7f51c4c57252048da15e13a6.jpg</filename>
	<path>image_1406_jpg.rf.f3963a2c7f51c4c57252048da15e13a6.jpg</path>
	<source>
		<database>roboflow.ai</database>
	</source>
	<size>
		<width>1920</width>
		<height>1080</height>
		<depth>3</depth>
	</size>
	<segmented>0</segmented>
	<object>
		<name>instance_salient_object</name>
		<pose>Unspecified</pose>
		<truncated>0</truncated>
		<difficult>0</difficult>
		<occluded>0</occluded>
		<bndbox>
			<xmin>1081</xmin>
			<xmax>1449</xmax>
			<ymin>535</ymin>
			<ymax>841</ymax>
		</bndbox>
	</object>
</annotation>
