<annotation>
	<folder></folder>
	<filename>image_81_jpg.rf.9a24cdc347661e6bf7e06e236b83b687.jpg</filename>
	<path>image_81_jpg.rf.9a24cdc347661e6bf7e06e236b83b687.jpg</path>
	<source>
		<database>roboflow.ai</database>
	</source>
	<size>
		<width>1920</width>
		<height>1080</height>
		<depth>3</depth>
	</size>
	<segmented>0</segmented>
	<object>
		<name>instance_salient_object</name>
		<pose>Unspecified</pose>
		<truncated>0</truncated>
		<difficult>0</difficult>
		<occluded>0</occluded>
		<bndbox>
			<xmin>1293</xmin>
			<xmax>1352</xmax>
			<ymin>492</ymin>
			<ymax>523</ymax>
		</bndbox>
	</object>
</annotation>
